{
  "notes": [
    {
      "id": "_3ADHccPyVUuLlB2po6Vv",
      "title": "my name is ",
      "details": "bijay kumar lama",
      "color": "#e91e63",
      "date": "Feb 07 2022",
      "favorite": true
    },
    {
      "id": "j-p27u6VnN762f_Em1Fy9",
      "title": "name",
      "details": "my name is bijay kumar lama my name is bijay kumar lama my name is bijay kumar lama my name is bijay kumar lama",
      "color": "#0F0E17",
      "date": "Feb 08 2022"
    },
    {
      "id": "MX5tvgKl-E_Ntr7xnMNdx",
      "title": "this is title",
      "details": "this is details body content.",
      "color": "#4caf50",
      "date": "Feb 08 2022",
      "favorite": false
    },
    {
      "id": "HSCfP0fET3cocCaHxmDKn",
      "title": "this is title2",
      "details": "this is details body content.2",
      "color": "#4caf50",
      "date": "Feb 08 2022"
    },
    {
      "id": "QKddMMN4R-SXSWbgKE1AT",
      "title": "tonight",
      "details": "tonight content ",
      "color": "#0F0E17",
      "date": "Feb 08 2022"
    },
    {
      "id": "T4S7zRG4VLzVVilPOmFf_",
      "title": "remember",
      "details": "remember content body ...",
      "color": "#ffeb3b",
      "date": "Feb 08 2022"
    },
    {
      "id": "rQJo3RAF0Tr4RruC7Omh-",
      "title": "this is title last",
      "details": "content last body",
      "color": "#03a9f4",
      "date": "Feb 08 2022"
    },
    {
      "id": "U_XqdIikybU2j0zboXU9v",
      "title": "title4",
      "details": "contain body 4",
      "color": "#8bc34a",
      "date": "Feb 08 2022"
    },
    {
      "id": "AXfwh2goZlWcmwES53n39",
      "title": "fd",
      "details": "",
      "color": "#0F0E17",
      "date": "Feb 08 2022"
    },
    {
      "id": "9lia3WnfYS53d7FMj5OAJ",
      "title": "vdsvs",
      "details": "fds",
      "color": "#607d8b",
      "date": "Feb 08 2022",
      "favorite": true
    },
    {
      "id": "5aJhIl1QiNPJtrPtcmlE-",
      "title": "last title",
      "details": "last content body",
      "color": "#f44336",
      "date": "Feb 08 2022"
    }
  ]
}